g2pk2/__init__.py
g2pk2/english.py
g2pk2/g2pk2.py
g2pk2/idioms.txt
g2pk2/numerals.py
g2pk2/regular.py
g2pk2/rules.txt
g2pk2/special.py
g2pk2/table.csv
g2pk2/utils.py
g2pk2-0.0.3.dist-info/LICENSE
g2pk2-0.0.3.dist-info/METADATA
g2pk2-0.0.3.dist-info/WHEEL
g2pk2-0.0.3.dist-info/top_level.txt
g2pk2-0.0.3.dist-info/RECORD
