Metadata-Version: 2.1
Name: g2pk2
Version: 0.0.3
Summary: g2pk2: updated folk of g2pk module
Home-page: https://github.com/tenebo/g2pk2
Author: tenebo
Author-email: tenebo@naver.com
License: Apache License 2.0
Classifier: Development Status :: 5 - Production/Stable
Classifier: Intended Audience :: Developers
Classifier: Intended Audience :: Science/Research
Classifier: License :: OSI Approved :: Apache Software License
Classifier: Operating System :: OS Independent
Classifier: Programming Language :: Python :: 3
Classifier: Programming Language :: Python :: 3.6
Classifier: Programming Language :: Python :: 3.7
Requires-Python: >=3.6
License-File: LICENSE
Requires-Dist: jamo
Requires-Dist: nltk
